{"_id":"n","_rev":"357-567288fbba7b19cc0e43e3b03fca3133","name":"n","description":"Interactively Manage All Your Node Versions","dist-tags":{"latest":"2.1.8"},"versions":{"0.0.1":{"name":"n","description":"node version manager","version":"0.0.1","author":{"name":"TJ Holowaychuk","email":"tj@vision-media.ca"},"keywords":["node","binary","version","env"],"bin":{"n":"./bin/n"},"engines":{"node":"*"},"_id":"n@0.0.1","_engineSupported":true,"_npmVersion":"0.2.13-1","_nodeVersion":"v0.2.6","dist":{"shasum":"876fe62a61e2d9fc8e1ac04937cac1e5974011a0","tarball":"https://registry.npmjs.org/n/-/n-0.0.1.tgz"},"directories":{}},"0.0.2":{"name":"n","description":"node version manager","version":"0.0.2","author":{"name":"TJ Holowaychuk","email":"tj@vision-media.ca"},"keywords":["node","binary","version","env"],"bin":{"n":"./bin/n"},"engines":{"node":"*"},"_id":"n@0.0.2","_engineSupported":true,"_npmVersion":"0.2.13-1","_nodeVersion":"v0.2.6","dist":{"shasum":"f99304226c9a4b80cbdd38e7c62bf2f6456ee14c","tarball":"https://registry.npmjs.org/n/-/n-0.0.2.tgz"},"directories":{}},"0.0.3":{"name":"n","description":"node version manager","version":"0.0.3","author":{"name":"TJ Holowaychuk","email":"tj@vision-media.ca"},"keywords":["node","binary","version","env"],"bin":{"n":"./bin/n"},"engines":{"node":"*"},"_id":"n@0.0.3","_engineSupported":true,"_npmVersion":"0.2.13-1","_nodeVersion":"v0.2.6","dist":{"shasum":"cfad2f1f5bc1649d8a682e0eda4cd223c9c8b759","tarball":"https://registry.npmjs.org/n/-/n-0.0.3.tgz"},"directories":{}},"0.0.4":{"name":"n","description":"node version manager","version":"0.0.4","author":{"name":"TJ Holowaychuk","email":"tj@vision-media.ca"},"keywords":["node","binary","version","env"],"bin":{"n":"./bin/n"},"engines":{"node":"*"},"_id":"n@0.0.4","_engineSupported":true,"_npmVersion":"0.2.13-1","_nodeVersion":"v0.2.5","dist":{"shasum":"60c67271f8d6b54892afdfd121a11eb0971f0ef1","tarball":"https://registry.npmjs.org/n/-/n-0.0.4.tgz"},"directories":{}},"0.1.0":{"name":"n","description":"node version manager","version":"0.1.0","author":{"name":"TJ Holowaychuk","email":"tj@vision-media.ca"},"keywords":["node","binary","version","env"],"bin":{"n":"./bin/n"},"engines":{"node":"*"},"_id":"n@0.1.0","_engineSupported":true,"_npmVersion":"0.2.13-1","_nodeVersion":"v0.2.5","dist":{"shasum":"79981e04e57ee4fb60ad48cf6d2d0e27530853f6","tarball":"https://registry.npmjs.org/n/-/n-0.1.0.tgz"},"directories":{}},"0.1.1":{"name":"n","description":"node version manager","version":"0.1.1","author":{"name":"TJ Holowaychuk","email":"tj@vision-media.ca"},"keywords":["node","binary","version","env"],"bin":{"n":"./bin/n"},"engines":{"node":"*"},"_id":"n@0.1.1","_engineSupported":true,"_npmVersion":"0.2.13-1","_nodeVersion":"v0.2.6","dist":{"shasum":"a585cf1d70de53f893bf4fd6e610c7fcde1068f5","tarball":"https://registry.npmjs.org/n/-/n-0.1.1.tgz"},"directories":{}},"0.1.2":{"name":"n","description":"node version manager","version":"0.1.2","author":{"name":"TJ Holowaychuk","email":"tj@vision-media.ca"},"keywords":["node","binary","version","env"],"bin":{"n":"./bin/n"},"engines":{"node":"*"},"_id":"n@0.1.2","_engineSupported":true,"_npmVersion":"0.2.15","_nodeVersion":"v0.2.6","directories":{"bin":"./bin"},"files":[""],"_defaultsLoaded":true,"dist":{"shasum":"767811ba70818e0e59821379303d7a72e7b1ab98","tarball":"https://registry.npmjs.org/n/-/n-0.1.2.tgz"}},"0.2.0":{"name":"n","description":"node version manager","version":"0.2.0","author":{"name":"TJ Holowaychuk","email":"tj@vision-media.ca"},"keywords":["node","binary","version","env"],"bin":{"n":"./bin/n"},"engines":{"node":"*"},"_id":"n@0.2.0","_engineSupported":true,"_npmVersion":"0.2.15","_nodeVersion":"v0.2.6","directories":{"bin":"./bin"},"files":[""],"_defaultsLoaded":true,"dist":{"shasum":"5f019f64ba4d6f333220b9a823a07415304b89b2","tarball":"https://registry.npmjs.org/n/-/n-0.2.0.tgz"}},"0.2.1":{"name":"n","description":"node version manager","version":"0.2.1","author":{"name":"TJ Holowaychuk","email":"tj@vision-media.ca"},"keywords":["node","binary","version","env"],"bin":{"n":"./bin/n"},"engines":{"node":"*"},"_id":"n@0.2.1","_engineSupported":true,"_npmVersion":"0.2.15","_nodeVersion":"v0.2.6","directories":{"bin":"./bin"},"files":[""],"_defaultsLoaded":true,"dist":{"shasum":"da59f6cbecd837f60b623af3ae95fcd4431fadd6","tarball":"https://registry.npmjs.org/n/-/n-0.2.1.tgz"}},"0.2.2":{"name":"n","description":"node version manager","version":"0.2.2","author":{"name":"TJ Holowaychuk","email":"tj@vision-media.ca"},"keywords":["node","binary","version","env"],"bin":{"n":"./bin/n"},"engines":{"node":"*"},"_id":"n@0.2.2","_engineSupported":true,"_npmVersion":"0.2.15","_nodeVersion":"v0.2.6","directories":{"bin":"./bin"},"files":[""],"_defaultsLoaded":true,"dist":{"shasum":"fcbae8fe641ebdcc4da9eedde1e0ebd2ed4044dd","tarball":"https://registry.npmjs.org/n/-/n-0.2.2.tgz"}},"0.3.0":{"name":"n","description":"node version manager","version":"0.3.0","author":{"name":"TJ Holowaychuk","email":"tj@vision-media.ca"},"keywords":["node","binary","version","env"],"bin":{"n":"./bin/n"},"engines":{"node":"*"},"_id":"n@0.3.0","_engineSupported":true,"_npmVersion":"0.2.15","_nodeVersion":"v0.3.5","directories":{"bin":"./bin"},"files":[""],"_defaultsLoaded":true,"dist":{"shasum":"aa8196967038841410b139f729b1cbdb1fa592b3","tarball":"https://registry.npmjs.org/n/-/n-0.3.0.tgz"}},"0.4.0":{"name":"n","description":"node version manager","version":"0.4.0","author":{"name":"TJ Holowaychuk","email":"tj@vision-media.ca"},"keywords":["node","binary","version","env"],"bin":{"n":"./bin/n"},"engines":{"node":"*"},"_id":"n@0.4.0","_engineSupported":true,"_npmVersion":"0.2.16","_nodeVersion":"v0.4.0","directories":{"bin":"./bin"},"files":[""],"_defaultsLoaded":true,"dist":{"shasum":"449feeba82ea9d0b64922266c1c79dd5c2adb73b","tarball":"https://registry.npmjs.org/n/-/n-0.4.0.tgz"}},"0.4.1":{"name":"n","description":"node version manager","version":"0.4.1","author":{"name":"TJ Holowaychuk","email":"tj@vision-media.ca"},"keywords":["node","binary","version","env"],"bin":{"n":"./bin/n"},"engines":{"node":"*"},"_id":"n@0.4.1","_engineSupported":true,"_npmVersion":"0.3.15","_nodeVersion":"v0.4.2","directories":{"bin":"./bin"},"files":[""],"_defaultsLoaded":true,"dist":{"shasum":"06dbe31b718b74b66e0d0366e03789809dfa6854","tarball":"https://registry.npmjs.org/n/-/n-0.4.1.tgz"}},"0.4.2":{"name":"n","description":"node version manager","version":"0.4.2","author":{"name":"TJ Holowaychuk","email":"tj@vision-media.ca"},"keywords":["node","binary","version","env"],"bin":{"n":"./bin/n"},"engines":{"node":"*"},"_npmJsonOpts":{"file":"/Users/tj/.npm/n/0.4.2/package/package.json","wscript":false,"contributors":false,"serverjs":false},"_id":"n@0.4.2","dependencies":{},"devDependencies":{},"_engineSupported":true,"_npmVersion":"1.0.14","_nodeVersion":"v0.4.10","_defaultsLoaded":true,"dist":{"shasum":"15e5bf340cc75f8d38f547659b44968f871fd6d7","tarball":"https://registry.npmjs.org/n/-/n-0.4.2.tgz"},"scripts":{},"maintainers":[{"name":"tjholowaychuk","email":"tj@vision-media.ca"}],"directories":{}},"0.5.0":{"name":"n","description":"node version manager","version":"0.5.0","author":{"name":"TJ Holowaychuk","email":"tj@vision-media.ca"},"keywords":["node","binary","version","env"],"bin":{"n":"./bin/n"},"engines":{"node":"*"},"_npmJsonOpts":{"file":"/Users/tj/.npm/n/0.5.0/package/package.json","wscript":false,"contributors":false,"serverjs":false},"_id":"n@0.5.0","dependencies":{},"devDependencies":{},"_engineSupported":true,"_npmVersion":"1.0.14","_nodeVersion":"v0.4.10","_defaultsLoaded":true,"dist":{"shasum":"d2a5435590504ac46a3193327881bd0322527570","tarball":"https://registry.npmjs.org/n/-/n-0.5.0.tgz"},"scripts":{},"maintainers":[{"name":"tjholowaychuk","email":"tj@vision-media.ca"}],"directories":{}},"0.5.1":{"name":"n","description":"node version manager","version":"0.5.1","author":{"name":"TJ Holowaychuk","email":"tj@vision-media.ca"},"keywords":["node","binary","version","env"],"bin":{"n":"./bin/n"},"engines":{"node":"*"},"_npmJsonOpts":{"file":"/Users/tj/.npm/n/0.5.1/package/package.json","wscript":false,"contributors":false,"serverjs":false},"_id":"n@0.5.1","dependencies":{},"devDependencies":{},"_engineSupported":true,"_npmVersion":"1.0.24","_nodeVersion":"v0.4.12","_defaultsLoaded":true,"dist":{"shasum":"9cb3c42e5dd1475905b0a1614578e6e18ae2dab3","tarball":"https://registry.npmjs.org/n/-/n-0.5.1.tgz"},"scripts":{},"maintainers":[{"name":"tjholowaychuk","email":"tj@vision-media.ca"}],"directories":{}},"0.5.2":{"name":"n","description":"node version manager","version":"0.5.2","author":{"name":"TJ Holowaychuk","email":"tj@vision-media.ca"},"keywords":["node","binary","version","env"],"bin":{"n":"./bin/n"},"engines":{"node":"*"},"_npmJsonOpts":{"file":"/Users/tj/.npm/n/0.5.2/package/package.json","wscript":false,"contributors":false,"serverjs":false},"_id":"n@0.5.2","dependencies":{},"devDependencies":{},"_engineSupported":true,"_npmVersion":"1.0.24","_nodeVersion":"v0.4.12","_defaultsLoaded":true,"dist":{"shasum":"f1fb1e20a20db44a35f66519833e5993437d3151","tarball":"https://registry.npmjs.org/n/-/n-0.5.2.tgz"},"scripts":{},"maintainers":[{"name":"tjholowaychuk","email":"tj@vision-media.ca"}],"directories":{}},"0.5.3":{"name":"n","description":"node version manager","version":"0.5.3","author":{"name":"TJ Holowaychuk","email":"tj@vision-media.ca"},"keywords":["node","binary","version","env"],"bin":{"n":"./bin/n"},"engines":{"node":"*"},"_npmUser":{"name":"tjholowaychuk","email":"tj@vision-media.ca"},"_id":"n@0.5.3","dependencies":{},"devDependencies":{},"_engineSupported":true,"_npmVersion":"1.0.103","_nodeVersion":"v0.5.10","_defaultsLoaded":true,"dist":{"shasum":"784c8183d259a5142ace64d6052ab46aa250344b","tarball":"https://registry.npmjs.org/n/-/n-0.5.3.tgz"},"maintainers":[{"name":"tjholowaychuk","email":"tj@vision-media.ca"}],"directories":{}},"0.5.4":{"name":"n","description":"node version manager","version":"0.5.4","author":{"name":"TJ Holowaychuk","email":"tj@vision-media.ca"},"keywords":["node","binary","version","env"],"bin":{"n":"./bin/n"},"engines":{"node":"*"},"_npmUser":{"name":"tjholowaychuk","email":"tj@vision-media.ca"},"_id":"n@0.5.4","dependencies":{},"devDependencies":{},"_engineSupported":true,"_npmVersion":"1.0.103","_nodeVersion":"v0.5.10","_defaultsLoaded":true,"dist":{"shasum":"193e92aa3efd0386ea1bd786d4cd7b028339fb09","tarball":"https://registry.npmjs.org/n/-/n-0.5.4.tgz"},"maintainers":[{"name":"tjholowaychuk","email":"tj@vision-media.ca"}],"directories":{}},"0.6.0":{"name":"n","description":"node version manager","version":"0.6.0","author":{"name":"TJ Holowaychuk","email":"tj@vision-media.ca"},"keywords":["node","binary","version","env"],"bin":{"n":"./bin/n"},"engines":{"node":"*"},"_npmUser":{"name":"tjholowaychuk","email":"tj@vision-media.ca"},"_id":"n@0.6.0","dependencies":{},"devDependencies":{},"_engineSupported":true,"_npmVersion":"1.0.106","_nodeVersion":"v0.6.8","_defaultsLoaded":true,"dist":{"shasum":"a888457cc245e7f24fa8a1071a58376584f874bb","tarball":"https://registry.npmjs.org/n/-/n-0.6.0.tgz"},"maintainers":[{"name":"tjholowaychuk","email":"tj@vision-media.ca"}],"directories":{}},"0.6.1":{"name":"n","description":"node version manager","version":"0.6.1","author":{"name":"TJ Holowaychuk","email":"tj@vision-media.ca"},"keywords":["node","binary","version","env"],"bin":{"n":"./bin/n"},"engines":{"node":"*"},"_npmUser":{"name":"tjholowaychuk","email":"tj@vision-media.ca"},"_id":"n@0.6.1","dependencies":{},"devDependencies":{},"_engineSupported":true,"_npmVersion":"1.0.106","_nodeVersion":"v0.4.12","_defaultsLoaded":true,"dist":{"shasum":"e1f72b04770f7ac1ba3ceefbd15e350c9246046d","tarball":"https://registry.npmjs.org/n/-/n-0.6.1.tgz"},"maintainers":[{"name":"tjholowaychuk","email":"tj@vision-media.ca"}],"directories":{}},"0.7.0":{"name":"n","description":"node version manager","version":"0.7.0","author":{"name":"TJ Holowaychuk","email":"tj@vision-media.ca"},"keywords":["node","binary","version","env"],"bin":{"n":"./bin/n"},"engines":{"node":"*"},"_npmUser":{"name":"tjholowaychuk","email":"tj@vision-media.ca"},"_id":"n@0.7.0","dependencies":{},"devDependencies":{},"_engineSupported":true,"_npmVersion":"1.0.106","_nodeVersion":"v0.6.10","_defaultsLoaded":true,"dist":{"shasum":"58f462db7fa9ba0b52a7e75750ae0b06b0c4d0c9","tarball":"https://registry.npmjs.org/n/-/n-0.7.0.tgz"},"maintainers":[{"name":"tjholowaychuk","email":"tj@vision-media.ca"}],"directories":{}},"0.7.1":{"name":"n","description":"node version manager","version":"0.7.1","author":{"name":"TJ Holowaychuk","email":"tj@vision-media.ca"},"keywords":["node","binary","version","env"],"bin":{"n":"./bin/n"},"engines":{"node":"*"},"_npmUser":{"name":"tjholowaychuk","email":"tj@vision-media.ca"},"_id":"n@0.7.1","dependencies":{},"devDependencies":{},"_engineSupported":true,"_npmVersion":"1.0.106","_nodeVersion":"v0.6.10","_defaultsLoaded":true,"dist":{"shasum":"5519fa39f2097d92caf6c2ff2c93de381d9d19cd","tarball":"https://registry.npmjs.org/n/-/n-0.7.1.tgz"},"maintainers":[{"name":"tjholowaychuk","email":"tj@vision-media.ca"}],"directories":{}},"0.7.2":{"name":"n","description":"node version manager","version":"0.7.2","author":{"name":"TJ Holowaychuk","email":"tj@vision-media.ca"},"homepage":"https://github.com/visionmedia/n","bugs":{"name":"https://github.com/visionmedia/n/issues"},"keywords":["node","binary","version","env"],"bin":{"n":"./bin/n"},"repository":{"type":"git","url":"git://github.com/visionmedia/n.git"},"engines":{"node":"*"},"_npmUser":{"name":"tjholowaychuk","email":"tj@vision-media.ca"},"_id":"n@0.7.2","dependencies":{},"devDependencies":{},"optionalDependencies":{},"_engineSupported":true,"_npmVersion":"1.1.24","_nodeVersion":"v0.6.19","_defaultsLoaded":true,"dist":{"shasum":"5fcd7e7d5b5fe54d649a9e613f0e3b8d4b030c9c","tarball":"https://registry.npmjs.org/n/-/n-0.7.2.tgz"},"maintainers":[{"name":"tjholowaychuk","email":"tj@vision-media.ca"}],"directories":{}},"0.7.3":{"name":"n","description":"node version manager","version":"0.7.3","author":{"name":"TJ Holowaychuk","email":"tj@vision-media.ca"},"homepage":"https://github.com/visionmedia/n","bugs":"https://github.com/visionmedia/n/issues","keywords":["node","binary","version","env"],"bin":{"n":"./bin/n"},"repository":{"type":"git","url":"git://github.com/visionmedia/n.git"},"engines":{"node":"*"},"_id":"n@0.7.3","dist":{"shasum":"90da9f9ce2e927d85bb271bf5b03e384563b7ac8","tarball":"https://registry.npmjs.org/n/-/n-0.7.3.tgz"},"maintainers":[{"name":"tjholowaychuk","email":"tj@vision-media.ca"}],"directories":{}},"0.8.0":{"name":"n","description":"node version manager","version":"0.8.0","author":{"name":"TJ Holowaychuk","email":"tj@vision-media.ca"},"homepage":"https://github.com/visionmedia/n","bugs":"https://github.com/visionmedia/n/issues","keywords":["node","binary","version","env"],"bin":{"n":"./bin/n"},"repository":{"type":"git","url":"git://github.com/visionmedia/n.git"},"engines":{"node":"*"},"_id":"n@0.8.0","dist":{"shasum":"e235ca63db4899891d12d04379b3ac35ad95dcbb","tarball":"https://registry.npmjs.org/n/-/n-0.8.0.tgz"},"_npmVersion":"1.2.0","_npmUser":{"name":"tjholowaychuk","email":"tj@vision-media.ca"},"maintainers":[{"name":"tjholowaychuk","email":"tj@vision-media.ca"}],"directories":{}},"0.8.1":{"name":"n","description":"node version manager","version":"0.8.1","author":{"name":"TJ Holowaychuk","email":"tj@vision-media.ca"},"homepage":"https://github.com/visionmedia/n","bugs":"https://github.com/visionmedia/n/issues","keywords":["node","binary","version","env"],"bin":{"n":"./bin/n"},"repository":{"type":"git","url":"git://github.com/visionmedia/n.git"},"engines":{"node":"*"},"_id":"n@0.8.1","dist":{"shasum":"39576355c2f47f4aded5a5fec9928d28f9bf53e3","tarball":"https://registry.npmjs.org/n/-/n-0.8.1.tgz"},"_npmVersion":"1.1.70","_npmUser":{"name":"tjholowaychuk","email":"tj@vision-media.ca"},"maintainers":[{"name":"tjholowaychuk","email":"tj@vision-media.ca"}],"directories":{}},"0.8.2":{"name":"n","description":"node version manager","version":"0.8.2","author":{"name":"TJ Holowaychuk","email":"tj@vision-media.ca"},"homepage":"https://github.com/visionmedia/n","bugs":"https://github.com/visionmedia/n/issues","keywords":["node","binary","version","env"],"bin":{"n":"./bin/n"},"repository":{"type":"git","url":"git://github.com/visionmedia/n.git"},"engines":{"node":"*"},"_id":"n@0.8.2","dist":{"shasum":"387632ae0b5fe964d8ce0d2992f4ddd114b8b898","tarball":"https://registry.npmjs.org/n/-/n-0.8.2.tgz"},"_npmVersion":"1.2.0","_npmUser":{"name":"tjholowaychuk","email":"tj@vision-media.ca"},"maintainers":[{"name":"tjholowaychuk","email":"tj@vision-media.ca"}],"directories":{}},"0.9.0":{"name":"n","description":"node version manager","version":"0.9.0","author":{"name":"TJ Holowaychuk","email":"tj@vision-media.ca"},"homepage":"https://github.com/visionmedia/n","bugs":"https://github.com/visionmedia/n/issues","keywords":["node","binary","version","env"],"bin":{"n":"./bin/n"},"repository":{"type":"git","url":"git://github.com/visionmedia/n.git"},"engines":{"node":"*"},"_id":"n@0.9.0","dist":{"shasum":"11d122c902bdb8bc5e9836540e8c838d6e71bc50","tarball":"https://registry.npmjs.org/n/-/n-0.9.0.tgz"},"_npmVersion":"1.1.66","_npmUser":{"name":"tjholowaychuk","email":"tj@vision-media.ca"},"maintainers":[{"name":"tjholowaychuk","email":"tj@vision-media.ca"}],"directories":{}},"0.9.1":{"name":"n","description":"node version manager","version":"0.9.1","author":{"name":"TJ Holowaychuk","email":"tj@vision-media.ca"},"homepage":"https://github.com/visionmedia/n","bugs":"https://github.com/visionmedia/n/issues","keywords":["node","binary","version","env"],"bin":{"n":"./bin/n"},"repository":{"type":"git","url":"git://github.com/visionmedia/n.git"},"engines":{"node":"*"},"_id":"n@0.9.1","dist":{"shasum":"17b01baded951680387f8dd0bc46d94c401e264d","tarball":"https://registry.npmjs.org/n/-/n-0.9.1.tgz"},"_npmVersion":"1.2.0","_npmUser":{"name":"tjholowaychuk","email":"tj@vision-media.ca"},"maintainers":[{"name":"tjholowaychuk","email":"tj@vision-media.ca"}],"directories":{}},"0.9.2":{"name":"n","description":"node version manager","version":"0.9.2","author":{"name":"TJ Holowaychuk","email":"tj@vision-media.ca"},"homepage":"https://github.com/visionmedia/n","bugs":"https://github.com/visionmedia/n/issues","keywords":["node","binary","version","env"],"bin":{"n":"./bin/n"},"repository":{"type":"git","url":"git://github.com/visionmedia/n.git"},"engines":{"node":"*"},"_id":"n@0.9.2","dist":{"shasum":"6b2506ed364acf385828fcbbb64b8a4e0d1da019","tarball":"https://registry.npmjs.org/n/-/n-0.9.2.tgz"},"_from":".","_npmVersion":"1.2.14","_npmUser":{"name":"bat","email":"ben@benatkin.com"},"maintainers":[{"name":"tjholowaychuk","email":"tj@vision-media.ca"},{"name":"bat","email":"ben@benatkin.com"}],"directories":{}},"0.9.3":{"name":"n","description":"node version manager","version":"0.9.3","author":{"name":"TJ Holowaychuk","email":"tj@vision-media.ca"},"homepage":"https://github.com/visionmedia/n","bugs":"https://github.com/visionmedia/n/issues","keywords":["node","binary","version","env"],"bin":{"n":"./bin/n"},"repository":{"type":"git","url":"git://github.com/visionmedia/n.git"},"engines":{"node":"*"},"_id":"n@0.9.3","dist":{"shasum":"ac06135b373c1c0f3631d611ebd25b1f35453f1b","tarball":"https://registry.npmjs.org/n/-/n-0.9.3.tgz"},"_from":".","_npmVersion":"1.2.14","_npmUser":{"name":"bat","email":"ben@benatkin.com"},"maintainers":[{"name":"tjholowaychuk","email":"tj@vision-media.ca"},{"name":"bat","email":"ben@benatkin.com"}],"directories":{}},"1.0.0":{"name":"n","description":"node version manager","version":"1.0.0","author":{"name":"TJ Holowaychuk","email":"tj@vision-media.ca"},"homepage":"https://github.com/visionmedia/n","bugs":"https://github.com/visionmedia/n/issues","keywords":["node","binary","version","env"],"bin":{"n":"./bin/n"},"repository":{"type":"git","url":"git://github.com/visionmedia/n.git"},"engines":{"node":"*"},"_id":"n@1.0.0","dist":{"shasum":"eb6e000b0bc222bcfe1352ad15ba2ac2bd615952","tarball":"https://registry.npmjs.org/n/-/n-1.0.0.tgz"},"_from":".","_npmVersion":"1.2.14","_npmUser":{"name":"tjholowaychuk","email":"tj@vision-media.ca"},"maintainers":[{"name":"tjholowaychuk","email":"tj@vision-media.ca"},{"name":"bat","email":"ben@benatkin.com"}],"directories":{}},"1.1.0":{"name":"n","description":"node version manager","version":"1.1.0","author":{"name":"TJ Holowaychuk","email":"tj@vision-media.ca"},"homepage":"https://github.com/visionmedia/n","bugs":{"url":"https://github.com/visionmedia/n/issues"},"keywords":["node","binary","version","env"],"bin":{"n":"./bin/n"},"repository":{"type":"git","url":"git://github.com/visionmedia/n.git"},"engines":{"node":"*"},"license":"MIT","_id":"n@1.1.0","dist":{"shasum":"0d49b9afba1577e237014b24a2dffc4e5d7f3e67","tarball":"https://registry.npmjs.org/n/-/n-1.1.0.tgz"},"_from":".","_npmVersion":"1.2.30","_npmUser":{"name":"tjholowaychuk","email":"tj@vision-media.ca"},"maintainers":[{"name":"tjholowaychuk","email":"tj@vision-media.ca"},{"name":"bat","email":"ben@benatkin.com"}],"directories":{}},"1.2.1":{"name":"n","description":"node version manager","version":"1.2.1","author":{"name":"TJ Holowaychuk","email":"tj@vision-media.ca"},"homepage":"https://github.com/visionmedia/n","bugs":{"url":"https://github.com/visionmedia/n/issues"},"keywords":["node","binary","version","env"],"bin":{"n":"./bin/n"},"repository":{"type":"git","url":"git://github.com/visionmedia/n.git"},"engines":{"node":"*"},"license":"MIT","_id":"n@1.2.1","dist":{"shasum":"7cd5c504519943eda2c264f445ed97e4be51a250","tarball":"https://registry.npmjs.org/n/-/n-1.2.1.tgz"},"_from":".","_npmVersion":"1.3.15","_npmUser":{"name":"tjholowaychuk","email":"tj@vision-media.ca"},"maintainers":[{"name":"tjholowaychuk","email":"tj@vision-media.ca"},{"name":"bat","email":"ben@benatkin.com"}],"directories":{}},"1.2.2":{"name":"n","description":"node version manager","version":"1.2.2","author":{"name":"TJ Holowaychuk","email":"tj@vision-media.ca"},"homepage":"https://github.com/visionmedia/n","bugs":{"url":"https://github.com/visionmedia/n/issues"},"keywords":["node","binary","version","env"],"bin":{"n":"./bin/n"},"repository":{"type":"git","url":"git://github.com/visionmedia/n.git"},"engines":{"node":"*"},"license":"MIT","gitHead":"453926629fd490447cfde10fdc50b463114ff00d","_id":"n@1.2.2","scripts":{},"_shasum":"67d86d39b2def181c660c117a07f32a26c111254","_from":".","_npmVersion":"1.4.14","_npmUser":{"name":"tjwebb","email":"me@traviswebb.com"},"maintainers":[{"name":"tjholowaychuk","email":"tj@vision-media.ca"},{"name":"bat","email":"ben@benatkin.com"},{"name":"tjwebb","email":"me@traviswebb.com"}],"dist":{"shasum":"67d86d39b2def181c660c117a07f32a26c111254","tarball":"https://registry.npmjs.org/n/-/n-1.2.2.tgz"},"directories":{}},"1.2.3":{"name":"n","description":"node version manager","version":"1.2.3","author":{"name":"TJ Holowaychuk","email":"tj@vision-media.ca"},"homepage":"https://github.com/visionmedia/n","bugs":{"url":"https://github.com/visionmedia/n/issues"},"keywords":["node","binary","version","env"],"bin":{"n":"./bin/n"},"repository":{"type":"git","url":"git://github.com/visionmedia/n.git"},"engines":{"node":"*"},"license":"MIT","gitHead":"84620228f9f9f43774542366eb6e2037d1fd5661","_id":"n@1.2.3","scripts":{},"_shasum":"397985d6eb110247ad06f5227f3b9c0b13f4c8c1","_from":".","_npmVersion":"1.4.14","_npmUser":{"name":"tjwebb","email":"me@traviswebb.com"},"maintainers":[{"name":"tjholowaychuk","email":"tj@vision-media.ca"},{"name":"bat","email":"ben@benatkin.com"},{"name":"tjwebb","email":"me@traviswebb.com"}],"dist":{"shasum":"397985d6eb110247ad06f5227f3b9c0b13f4c8c1","tarball":"https://registry.npmjs.org/n/-/n-1.2.3.tgz"},"directories":{}},"1.2.4":{"name":"n","description":"node version manager","version":"1.2.4","author":{"name":"TJ Holowaychuk","email":"tj@vision-media.ca"},"homepage":"https://github.com/visionmedia/n","bugs":{"url":"https://github.com/visionmedia/n/issues"},"keywords":["node","binary","version","env"],"bin":{"n":"./bin/n"},"repository":{"type":"git","url":"git://github.com/visionmedia/n.git"},"engines":{"node":"*"},"license":"MIT","gitHead":"48aa94f3032d9e20f11826518c9fe7c78b98f28e","_id":"n@1.2.4","scripts":{},"_shasum":"6d51155077ddc670e9607a26551632e309ee9771","_from":".","_npmVersion":"1.4.14","_npmUser":{"name":"tjwebb","email":"me@traviswebb.com"},"maintainers":[{"name":"tjholowaychuk","email":"tj@vision-media.ca"},{"name":"bat","email":"ben@benatkin.com"},{"name":"tjwebb","email":"me@traviswebb.com"}],"dist":{"shasum":"6d51155077ddc670e9607a26551632e309ee9771","tarball":"https://registry.npmjs.org/n/-/n-1.2.4.tgz"},"directories":{}},"1.2.5":{"name":"n","description":"node version manager","version":"1.2.5","author":{"name":"TJ Holowaychuk","email":"tj@vision-media.ca"},"homepage":"https://github.com/visionmedia/n","bugs":{"url":"https://github.com/visionmedia/n/issues"},"keywords":["node","binary","version","env"],"bin":{"n":"./bin/n"},"repository":{"type":"git","url":"git://github.com/visionmedia/n.git"},"engines":{"node":"*"},"license":"MIT","gitHead":"45b3d4a5b28dd4911f502f41ffcfb47bfc216cca","_id":"n@1.2.5","scripts":{},"_shasum":"4fabf3d3492767b47340d05a0513a653204db6fd","_from":".","_npmVersion":"1.4.14","_npmUser":{"name":"tjwebb","email":"me@traviswebb.com"},"maintainers":[{"name":"tjholowaychuk","email":"tj@vision-media.ca"},{"name":"bat","email":"ben@benatkin.com"},{"name":"tjwebb","email":"me@traviswebb.com"}],"dist":{"shasum":"4fabf3d3492767b47340d05a0513a653204db6fd","tarball":"https://registry.npmjs.org/n/-/n-1.2.5.tgz"},"directories":{}},"1.2.6":{"name":"n","description":"node version manager","version":"1.2.6","author":{"name":"TJ Holowaychuk","email":"tj@vision-media.ca"},"homepage":"https://github.com/visionmedia/n","bugs":{"url":"https://github.com/visionmedia/n/issues"},"keywords":["node","binary","version","env"],"bin":{"n":"./bin/n"},"repository":{"type":"git","url":"git://github.com/visionmedia/n.git"},"engines":{"node":"*"},"license":"MIT","gitHead":"d9d557bf91790cd6e8fb7dc9404e48ad9af6a474","_id":"n@1.2.6","scripts":{},"_shasum":"989bea6dbc9216a2b9cb9e210aacf1ab7b06e59b","_from":".","_npmVersion":"1.4.14","_npmUser":{"name":"tjwebb","email":"me@traviswebb.com"},"maintainers":[{"name":"tjholowaychuk","email":"tj@vision-media.ca"},{"name":"bat","email":"ben@benatkin.com"},{"name":"tjwebb","email":"me@traviswebb.com"}],"dist":{"shasum":"989bea6dbc9216a2b9cb9e210aacf1ab7b06e59b","tarball":"https://registry.npmjs.org/n/-/n-1.2.6.tgz"},"directories":{}},"1.2.7":{"name":"n","description":"node version manager","version":"1.2.7","author":{"name":"TJ Holowaychuk","email":"tj@vision-media.ca"},"homepage":"https://github.com/visionmedia/n","bugs":{"url":"https://github.com/visionmedia/n/issues"},"keywords":["node","binary","version","env"],"bin":{"n":"./bin/n"},"repository":{"type":"git","url":"git://github.com/visionmedia/n.git"},"engines":{"node":"*"},"license":"MIT","gitHead":"a78a512ea87bdb4b3fb51b4edd8a115f00596649","_id":"n@1.2.7","scripts":{},"_shasum":"6376f83aca6a08b9539544d0151319ccb2240e32","_from":".","_npmVersion":"1.4.14","_npmUser":{"name":"tjwebb","email":"me@traviswebb.com"},"maintainers":[{"name":"tjholowaychuk","email":"tj@vision-media.ca"},{"name":"bat","email":"ben@benatkin.com"},{"name":"tjwebb","email":"me@traviswebb.com"}],"dist":{"shasum":"6376f83aca6a08b9539544d0151319ccb2240e32","tarball":"https://registry.npmjs.org/n/-/n-1.2.7.tgz"},"directories":{}},"1.2.8":{"name":"n","description":"node version manager","version":"1.2.8","author":{"name":"TJ Holowaychuk","email":"tj@vision-media.ca"},"homepage":"https://github.com/visionmedia/n","bugs":{"url":"https://github.com/visionmedia/n/issues"},"keywords":["node","binary","version","manager","switcher","env"],"bin":{"n":"./bin/n"},"repository":{"type":"git","url":"git://github.com/visionmedia/n.git"},"preferGlobal":true,"os":["!win32"],"engines":{"node":"*"},"license":"MIT","gitHead":"39b8d6a44deea20002c9c394d51552e2c454828c","_id":"n@1.2.8","scripts":{},"_shasum":"89ce8475f1fdba5d98b785032628bc742aadd48c","_from":".","_npmVersion":"1.4.14","_npmUser":{"name":"tjwebb","email":"me@traviswebb.com"},"maintainers":[{"name":"tjholowaychuk","email":"tj@vision-media.ca"},{"name":"bat","email":"ben@benatkin.com"},{"name":"tjwebb","email":"me@traviswebb.com"}],"dist":{"shasum":"89ce8475f1fdba5d98b785032628bc742aadd48c","tarball":"https://registry.npmjs.org/n/-/n-1.2.8.tgz"},"directories":{}},"1.2.9":{"name":"n","description":"node version manager","version":"1.2.9","author":{"name":"TJ Holowaychuk","email":"tj@vision-media.ca"},"homepage":"https://github.com/visionmedia/n","bugs":{"url":"https://github.com/visionmedia/n/issues"},"keywords":["node","binary","version","manager","switcher","env"],"bin":{"n":"./bin/n"},"repository":{"type":"git","url":"git://github.com/visionmedia/n.git"},"preferGlobal":true,"os":["!win32"],"engines":{"node":"*"},"license":"MIT","_id":"n@1.2.9","_shasum":"962f4a31f218e0e03d4353e68311d4bbe38cf130","_from":".","_npmVersion":"1.4.9","_npmUser":{"name":"tjwebb","email":"me@traviswebb.com"},"maintainers":[{"name":"tjholowaychuk","email":"tj@vision-media.ca"},{"name":"bat","email":"ben@benatkin.com"},{"name":"tjwebb","email":"me@traviswebb.com"}],"dist":{"shasum":"962f4a31f218e0e03d4353e68311d4bbe38cf130","tarball":"https://registry.npmjs.org/n/-/n-1.2.9.tgz"},"directories":{}},"1.2.11":{"name":"n","description":"node version manager","version":"1.2.11","author":{"name":"TJ Holowaychuk","email":"tj@vision-media.ca"},"homepage":"https://github.com/visionmedia/n","bugs":{"url":"https://github.com/visionmedia/n/issues"},"contributors":[{"name":"Travis Webb","email":"me@traviswebb.com","url":"tjw.io"}],"keywords":["node","binary","version","manager","switcher","env"],"bin":{"n":"./bin/n"},"repository":{"type":"git","url":"git://github.com/visionmedia/n.git"},"preferGlobal":true,"os":["!win32"],"engines":{"node":"*"},"license":"MIT","_id":"n@1.2.11","dist":{"shasum":"7d4713a9ad77a5f49c805e8ae2a65ac025fcea0f","tarball":"https://registry.npmjs.org/n/-/n-1.2.11.tgz"},"_from":".","_npmVersion":"1.2.30","_npmUser":{"name":"tjwebb","email":"me@traviswebb.com"},"maintainers":[{"name":"tjholowaychuk","email":"tj@vision-media.ca"},{"name":"bat","email":"ben@benatkin.com"},{"name":"tjwebb","email":"me@traviswebb.com"}],"directories":{}},"1.2.13":{"name":"n","description":"node version manager","version":"1.2.13","author":{"name":"TJ Holowaychuk","email":"tj@vision-media.ca"},"homepage":"https://github.com/tj/n","bugs":{"url":"https://github.com/tj/n/issues"},"contributors":[{"name":"Travis Webb","email":"me@traviswebb.com","url":"tjw.io"}],"keywords":["nvm","node","version","manager","switcher","node","binary","env"],"bin":{"n":"./bin/n"},"repository":{"type":"git","url":"git://github.com/tj/n.git"},"preferGlobal":true,"os":["!win32"],"engines":{"node":"*"},"license":"MIT","_id":"n@1.2.13","dist":{"shasum":"90922391ba49e2386ae316370915085042074190","tarball":"https://registry.npmjs.org/n/-/n-1.2.13.tgz"},"_from":".","_npmVersion":"1.2.30","_npmUser":{"name":"tjwebb","email":"me@traviswebb.com"},"maintainers":[{"name":"tjholowaychuk","email":"tj@vision-media.ca"},{"name":"bat","email":"ben@benatkin.com"},{"name":"tjwebb","email":"me@traviswebb.com"}],"directories":{}},"1.2.14":{"name":"n","description":"node version manager","version":"1.2.14","author":{"name":"TJ Holowaychuk","email":"tj@vision-media.ca"},"homepage":"https://github.com/tj/n","bugs":{"url":"https://github.com/tj/n/issues"},"contributors":[{"name":"Travis Webb","email":"me@traviswebb.com","url":"tjw.io"}],"keywords":["nvm","node","version","manager","switcher","node","binary","env"],"bin":{"n":"./bin/n"},"repository":{"type":"git","url":"git://github.com/tj/n.git"},"preferGlobal":true,"os":["!win32"],"engines":{"node":"*"},"license":"MIT","gitHead":"8c05c5ab2633bc55def0bcb79351598a60c6f66f","_id":"n@1.2.14","scripts":{},"_shasum":"7077636af32fc7e7303e33a99945d6135dc78020","_from":".","_npmVersion":"2.3.0","_nodeVersion":"0.11.16","_npmUser":{"name":"tjwebb","email":"me@traviswebb.com"},"maintainers":[{"name":"tjholowaychuk","email":"tj@vision-media.ca"},{"name":"bat","email":"ben@benatkin.com"},{"name":"tjwebb","email":"me@traviswebb.com"}],"dist":{"shasum":"7077636af32fc7e7303e33a99945d6135dc78020","tarball":"https://registry.npmjs.org/n/-/n-1.2.14.tgz"},"directories":{}},"1.3.0":{"name":"n","description":"node version manager","version":"1.3.0","author":{"name":"TJ Holowaychuk","email":"tj@vision-media.ca"},"homepage":"https://github.com/tj/n","bugs":{"url":"https://github.com/tj/n/issues"},"contributors":[{"name":"Travis Webb","email":"me@traviswebb.com","url":"tjw.io"}],"keywords":["nvm","node","version","manager","switcher","node","binary","env"],"bin":{"n":"./bin/n"},"repository":{"type":"git","url":"git://github.com/tj/n.git"},"preferGlobal":true,"os":["!win32"],"engines":{"node":"*"},"license":"MIT","gitHead":"ab194b3b1ca8539b2b1f9f9755d1401a667d0a95","_id":"n@1.3.0","scripts":{},"_shasum":"95afad80d2c73e89151efc0b4e6a8905cbb8ed2d","_from":".","_npmVersion":"1.4.28","_npmUser":{"name":"tjwebb","email":"me@traviswebb.com"},"maintainers":[{"name":"tjholowaychuk","email":"tj@vision-media.ca"},{"name":"bat","email":"ben@benatkin.com"},{"name":"tjwebb","email":"me@traviswebb.com"}],"dist":{"shasum":"95afad80d2c73e89151efc0b4e6a8905cbb8ed2d","tarball":"https://registry.npmjs.org/n/-/n-1.3.0.tgz"},"directories":{}},"1.4.0":{"name":"n","description":"node version manager","version":"1.4.0","author":{"name":"TJ Holowaychuk","email":"tj@vision-media.ca"},"homepage":"https://github.com/tj/n","bugs":{"url":"https://github.com/tj/n/issues"},"contributors":[{"name":"Travis Webb","email":"me@traviswebb.com","url":"tjw.io"}],"keywords":["nvm","node","version","manager","switcher","node","binary","env"],"bin":{"n":"./bin/n"},"repository":{"type":"git","url":"git://github.com/tj/n.git"},"preferGlobal":true,"os":["!win32"],"engines":{"node":"*"},"license":"MIT","gitHead":"93689ade05b2ea9d054a9e919647ab96d9ee483b","_id":"n@1.4.0","scripts":{},"_shasum":"5d48ede3861b3fd476a8309a3b121232b56814c7","_from":".","_npmVersion":"2.11.3","_nodeVersion":"0.12.7","_npmUser":{"name":"maxrimue","email":"max.rittmueller@gmail.com"},"dist":{"shasum":"5d48ede3861b3fd476a8309a3b121232b56814c7","tarball":"https://registry.npmjs.org/n/-/n-1.4.0.tgz"},"maintainers":[{"name":"tjholowaychuk","email":"tj@vision-media.ca"},{"name":"bat","email":"ben@benatkin.com"},{"name":"tjwebb","email":"me@traviswebb.com"},{"name":"troy0820","email":"troy.connor@yahoo.com"},{"name":"qw3rtman","email":"nimit@nimitkalra.com"},{"name":"maxrimue","email":"max.rittmueller@gmail.com"}],"directories":{}},"2.0.0":{"name":"n","description":"node version manager","version":"2.0.0","author":{"name":"TJ Holowaychuk","email":"tj@vision-media.ca"},"homepage":"https://github.com/tj/n","bugs":{"url":"https://github.com/tj/n/issues"},"contributors":[{"name":"Travis Webb","email":"me@traviswebb.com","url":"tjw.io"}],"keywords":["nvm","node","version","manager","switcher","node","binary","env"],"bin":{"n":"./bin/n"},"repository":{"type":"git","url":"git://github.com/tj/n.git"},"preferGlobal":true,"os":["!win32"],"engines":{"node":"*"},"license":"MIT","gitHead":"3aada4335f91c487eb529b5abfa79ed749429fed","_id":"n@2.0.0","scripts":{},"_shasum":"97147a3cbaeec64ddbfefde4bf772faf3921d3c9","_from":".","_npmVersion":"2.11.3","_nodeVersion":"0.12.7","_npmUser":{"name":"maxrimue","email":"max.rittmueller@gmail.com"},"dist":{"shasum":"97147a3cbaeec64ddbfefde4bf772faf3921d3c9","tarball":"https://registry.npmjs.org/n/-/n-2.0.0.tgz"},"maintainers":[{"name":"tjholowaychuk","email":"tj@vision-media.ca"},{"name":"bat","email":"ben@benatkin.com"},{"name":"tjwebb","email":"me@traviswebb.com"},{"name":"troy0820","email":"troy.connor@yahoo.com"},{"name":"qw3rtman","email":"nimit@nimitkalra.com"},{"name":"maxrimue","email":"max.rittmueller@gmail.com"}],"directories":{}},"1.4.1":{"name":"n","description":"node version manager","version":"1.4.1","author":{"name":"TJ Holowaychuk","email":"tj@vision-media.ca"},"homepage":"https://github.com/tj/n","bugs":{"url":"https://github.com/tj/n/issues"},"contributors":[{"name":"Travis Webb","email":"me@traviswebb.com","url":"tjw.io"}],"keywords":["nvm","node","version","manager","switcher","node","binary","env"],"bin":{"n":"./bin/n"},"repository":{"type":"git","url":"git://github.com/tj/n.git"},"preferGlobal":true,"os":["!win32"],"engines":{"node":"*"},"license":"MIT","gitHead":"62d0d54416b0e8210466a6fa16f28fd36caba11c","_id":"n@1.4.1","scripts":{},"_shasum":"e91830019e6c0dbd23baf38a0c49ceddb5b1131a","_from":".","_npmVersion":"2.11.3","_nodeVersion":"0.12.7","_npmUser":{"name":"maxrimue","email":"max.rittmueller@gmail.com"},"dist":{"shasum":"e91830019e6c0dbd23baf38a0c49ceddb5b1131a","tarball":"https://registry.npmjs.org/n/-/n-1.4.1.tgz"},"maintainers":[{"name":"tjholowaychuk","email":"tj@vision-media.ca"},{"name":"bat","email":"ben@benatkin.com"},{"name":"tjwebb","email":"me@traviswebb.com"},{"name":"troy0820","email":"troy.connor@yahoo.com"},{"name":"qw3rtman","email":"nimit@nimitkalra.com"},{"name":"maxrimue","email":"max.rittmueller@gmail.com"}],"directories":{}},"2.0.1":{"name":"n","description":"node version manager","version":"2.0.1","author":{"name":"TJ Holowaychuk","email":"tj@vision-media.ca"},"homepage":"https://github.com/tj/n","bugs":{"url":"https://github.com/tj/n/issues"},"contributors":[{"name":"Travis Webb","email":"me@traviswebb.com","url":"tjw.io"}],"keywords":["nvm","node","version","manager","switcher","node","binary","env"],"bin":{"n":"./bin/n"},"repository":{"type":"git","url":"git://github.com/tj/n.git"},"preferGlobal":true,"os":["!win32"],"engines":{"node":"*"},"license":"MIT","gitHead":"2a400cc83570535d0f5aa9f4dbae793095abc31f","_id":"n@2.0.1","scripts":{},"_shasum":"b327196797e9cd2d48f6d1fe6a8191ec4a92c4c1","_from":".","_npmVersion":"2.11.3","_nodeVersion":"0.12.7","_npmUser":{"name":"maxrimue","email":"max.rittmueller@gmail.com"},"dist":{"shasum":"b327196797e9cd2d48f6d1fe6a8191ec4a92c4c1","tarball":"https://registry.npmjs.org/n/-/n-2.0.1.tgz"},"maintainers":[{"name":"tjholowaychuk","email":"tj@vision-media.ca"},{"name":"bat","email":"ben@benatkin.com"},{"name":"tjwebb","email":"me@traviswebb.com"},{"name":"troy0820","email":"troy.connor@yahoo.com"},{"name":"qw3rtman","email":"nimit@nimitkalra.com"},{"name":"maxrimue","email":"max.rittmueller@gmail.com"}],"directories":{}},"1.4.2":{"name":"n","description":"node version manager","version":"1.4.2","author":{"name":"TJ Holowaychuk","email":"tj@vision-media.ca"},"homepage":"https://github.com/tj/n","bugs":{"url":"https://github.com/tj/n/issues"},"contributors":[{"name":"Travis Webb","email":"me@traviswebb.com","url":"tjw.io"}],"keywords":["nvm","node","version","manager","switcher","node","binary","env"],"bin":{"n":"./bin/n"},"repository":{"type":"git","url":"git://github.com/tj/n.git"},"preferGlobal":true,"os":["!win32"],"engines":{"node":"*"},"license":"MIT","gitHead":"42ae0c833f5bfc4878eed95994d261277449c517","_id":"n@1.4.2","scripts":{},"_shasum":"5985f67352c491371a7dd6ff48745aff371970cf","_from":".","_npmVersion":"2.13.4","_nodeVersion":"0.12.7","_npmUser":{"name":"maxrimue","email":"max.rittmueller@gmail.com"},"dist":{"shasum":"5985f67352c491371a7dd6ff48745aff371970cf","tarball":"https://registry.npmjs.org/n/-/n-1.4.2.tgz"},"maintainers":[{"name":"tjholowaychuk","email":"tj@vision-media.ca"},{"name":"bat","email":"ben@benatkin.com"},{"name":"tjwebb","email":"me@traviswebb.com"},{"name":"troy0820","email":"troy.connor@yahoo.com"},{"name":"qw3rtman","email":"nimit@nimitkalra.com"},{"name":"maxrimue","email":"max.rittmueller@gmail.com"},{"name":"tedgaydos","email":"tedgaydos@gmail.com"}],"directories":{}},"2.0.2":{"name":"n","description":"node version manager","version":"2.0.2","author":{"name":"TJ Holowaychuk","email":"tj@vision-media.ca"},"homepage":"https://github.com/tj/n","bugs":{"url":"https://github.com/tj/n/issues"},"contributors":[{"name":"Travis Webb","email":"me@traviswebb.com","url":"tjw.io"}],"keywords":["nvm","node","version","manager","switcher","node","binary","env"],"bin":{"n":"./bin/n"},"repository":{"type":"git","url":"git://github.com/tj/n.git"},"preferGlobal":true,"os":["!win32"],"engines":{"node":"*"},"license":"MIT","gitHead":"7831e76a57429afc6341a583febb99469db4d1dc","_id":"n@2.0.2","scripts":{},"_shasum":"1d132d1e33c8687bae54313792626e7878bd5f57","_from":".","_npmVersion":"2.13.4","_nodeVersion":"0.12.7","_npmUser":{"name":"maxrimue","email":"max.rittmueller@gmail.com"},"dist":{"shasum":"1d132d1e33c8687bae54313792626e7878bd5f57","tarball":"https://registry.npmjs.org/n/-/n-2.0.2.tgz"},"maintainers":[{"name":"tjholowaychuk","email":"tj@vision-media.ca"},{"name":"bat","email":"ben@benatkin.com"},{"name":"tjwebb","email":"me@traviswebb.com"},{"name":"troy0820","email":"troy.connor@yahoo.com"},{"name":"qw3rtman","email":"nimit@nimitkalra.com"},{"name":"maxrimue","email":"max.rittmueller@gmail.com"},{"name":"tedgaydos","email":"tedgaydos@gmail.com"}],"directories":{}},"2.1.0":{"name":"n","description":"Interactively Manage All Your Node Versions","version":"2.1.0","author":{"name":"TJ Holowaychuk","email":"tj@vision-media.ca"},"homepage":"https://github.com/tj/n","bugs":{"url":"https://github.com/tj/n/issues"},"contributors":[{"name":"Travis Webb","email":"me@traviswebb.com","url":"tjw.io"},{"name":"Nimit Kalra","email":"me@nimit.io","url":"http://nimit.io"},{"name":"Troy Connor","email":"troy0820@gmail.com","url":"https://github.com/troy0820"}],"keywords":["nvm","node","version","manager","switcher","node","binary","env"],"bin":{"n":"./bin/n"},"repository":{"type":"git","url":"git://github.com/tj/n.git"},"preferGlobal":true,"os":["!win32"],"engines":{"node":"*"},"license":"MIT","gitHead":"17ef0bf936c9ddb57b174d79f81ae04d8257883e","_id":"n@2.1.0","scripts":{},"_shasum":"4fc736dc18291e464c79fda9ef8faf21e6e1a679","_from":".","_npmVersion":"3.3.12","_nodeVersion":"5.3.0","_npmUser":{"name":"qw3rtman","email":"me@nimit.io"},"dist":{"shasum":"4fc736dc18291e464c79fda9ef8faf21e6e1a679","tarball":"https://registry.npmjs.org/n/-/n-2.1.0.tgz"},"maintainers":[{"name":"bat","email":"ben@benatkin.com"},{"name":"qw3rtman","email":"nimit@nimitkalra.com"},{"name":"tedgaydos","email":"tedgaydos@gmail.com"},{"name":"tjholowaychuk","email":"tj@vision-media.ca"},{"name":"tjwebb","email":"me@traviswebb.com"},{"name":"troy0820","email":"troy.connor@yahoo.com"}],"directories":{}},"2.1.1":{"name":"n","description":"Interactively Manage All Your Node Versions","version":"2.1.1","author":{"name":"TJ Holowaychuk","email":"tj@vision-media.ca"},"homepage":"https://github.com/tj/n","bugs":{"url":"https://github.com/tj/n/issues"},"contributors":[{"name":"Travis Webb","email":"me@traviswebb.com","url":"tjw.io"},{"name":"Nimit Kalra","email":"me@nimit.io","url":"http://nimit.io"},{"name":"Troy Connor","email":"troy0820@gmail.com","url":"https://github.com/troy0820"}],"keywords":["nvm","node","version","manager","switcher","node","binary","env"],"bin":{"n":"./bin/n"},"repository":{"type":"git","url":"git://github.com/tj/n.git"},"preferGlobal":true,"os":["!win32"],"engines":{"node":"*"},"license":"MIT","gitHead":"f91850a162e17e3ea0874fa54146fb383d1246bc","_id":"n@2.1.1","scripts":{},"_shasum":"f6d764a08f41341995014d472e3a501356f4dd4c","_from":".","_npmVersion":"3.8.9","_nodeVersion":"6.2.0","_npmUser":{"name":"qw3rtman","email":"me@nimit.io"},"dist":{"shasum":"f6d764a08f41341995014d472e3a501356f4dd4c","tarball":"https://registry.npmjs.org/n/-/n-2.1.1.tgz"},"maintainers":[{"name":"bat","email":"ben@benatkin.com"},{"name":"qw3rtman","email":"nimit@nimitkalra.com"},{"name":"tedgaydos","email":"tedgaydos@gmail.com"},{"name":"tjholowaychuk","email":"tj@vision-media.ca"},{"name":"tjwebb","email":"me@traviswebb.com"},{"name":"troy0820","email":"troy.connor@yahoo.com"}],"_npmOperationalInternal":{"host":"packages-16-east.internal.npmjs.com","tmp":"tmp/n-2.1.1.tgz_1466036411955_0.21519096451811492"},"directories":{}},"2.1.2":{"name":"n","description":"Interactively Manage All Your Node Versions","version":"2.1.2","author":{"name":"TJ Holowaychuk","email":"tj@vision-media.ca"},"homepage":"https://github.com/tj/n","bugs":{"url":"https://github.com/tj/n/issues"},"contributors":[{"name":"Travis Webb","email":"me@traviswebb.com","url":"tjw.io"},{"name":"Nimit Kalra","email":"me@nimit.io","url":"http://nimit.io"},{"name":"Troy Connor","email":"troy0820@gmail.com","url":"https://github.com/troy0820"}],"keywords":["nvm","node","version","manager","switcher","node","binary","env"],"bin":{"n":"./bin/n"},"repository":{"type":"git","url":"git://github.com/tj/n.git"},"preferGlobal":true,"os":["!win32"],"engines":{"node":"*"},"license":"MIT","gitHead":"82d104f887a4ca20566190e8328a64dc3e61754f","_id":"n@2.1.2","scripts":{},"_shasum":"09bacf76983f47c6c91f85cecb2f96e38d4dad7a","_from":".","_npmVersion":"3.9.5","_nodeVersion":"6.2.2","_npmUser":{"name":"qw3rtman","email":"me@nimit.io"},"dist":{"shasum":"09bacf76983f47c6c91f85cecb2f96e38d4dad7a","tarball":"https://registry.npmjs.org/n/-/n-2.1.2.tgz"},"maintainers":[{"name":"bat","email":"ben@benatkin.com"},{"name":"qw3rtman","email":"nimit@nimitkalra.com"},{"name":"tedgaydos","email":"tedgaydos@gmail.com"},{"name":"tjholowaychuk","email":"tj@vision-media.ca"},{"name":"tjwebb","email":"me@traviswebb.com"},{"name":"troy0820","email":"troy.connor@yahoo.com"}],"_npmOperationalInternal":{"host":"packages-12-west.internal.npmjs.com","tmp":"tmp/n-2.1.2.tgz_1467703234844_0.7033454356715083"},"directories":{}},"2.1.3":{"name":"n","description":"Interactively Manage All Your Node Versions","version":"2.1.3","author":{"name":"TJ Holowaychuk","email":"tj@vision-media.ca"},"homepage":"https://github.com/tj/n","bugs":{"url":"https://github.com/tj/n/issues"},"contributors":[{"name":"Travis Webb","email":"me@traviswebb.com","url":"tjw.io"},{"name":"Nimit Kalra","email":"me@nimit.io","url":"http://nimit.io"},{"name":"Troy Connor","email":"troy0820@gmail.com","url":"https://github.com/troy0820"}],"keywords":["nvm","node","version","manager","switcher","node","binary","env"],"bin":{"n":"./bin/n"},"repository":{"type":"git","url":"git://github.com/tj/n.git"},"preferGlobal":true,"os":["!win32"],"engines":{"node":"*"},"license":"MIT","gitHead":"d0b3a2f8ba5d8b0d818f529cb188a6a967ddb7e8","_id":"n@2.1.3","scripts":{},"_shasum":"ea115a3d42111f97d2eb0775ef57f777129c8ad7","_from":".","_npmVersion":"2.15.8","_nodeVersion":"4.4.7","_npmUser":{"name":"qw3rtman","email":"me@nimit.io"},"dist":{"shasum":"ea115a3d42111f97d2eb0775ef57f777129c8ad7","tarball":"https://registry.npmjs.org/n/-/n-2.1.3.tgz"},"maintainers":[{"name":"bat","email":"ben@benatkin.com"},{"name":"qw3rtman","email":"nimit@nimitkalra.com"},{"name":"tedgaydos","email":"tedgaydos@gmail.com"},{"name":"tjholowaychuk","email":"tj@vision-media.ca"},{"name":"tjwebb","email":"me@traviswebb.com"},{"name":"troy0820","email":"troy.connor@yahoo.com"}],"_npmOperationalInternal":{"host":"packages-12-west.internal.npmjs.com","tmp":"tmp/n-2.1.3.tgz_1468352743217_0.9636592208407819"},"directories":{}},"2.1.4":{"name":"n","description":"Interactively Manage All Your Node Versions","version":"2.1.4","author":{"name":"TJ Holowaychuk","email":"tj@vision-media.ca"},"homepage":"https://github.com/tj/n","bugs":{"url":"https://github.com/tj/n/issues"},"contributors":[{"name":"Travis Webb","email":"me@traviswebb.com","url":"tjw.io"},{"name":"Nimit Kalra","email":"me@nimit.io","url":"http://nimit.io"},{"name":"Troy Connor","email":"troy0820@gmail.com","url":"https://github.com/troy0820"}],"keywords":["nvm","node","version","manager","switcher","node","binary","env"],"bin":{"n":"./bin/n"},"repository":{"type":"git","url":"git://github.com/tj/n.git"},"preferGlobal":true,"os":["!win32"],"engines":{"node":"*"},"license":"MIT","gitHead":"ff9ba303d972069903c0f951ece43f47adce24e8","_id":"n@2.1.4","scripts":{},"_shasum":"7546bc467a120cc96718f2716cd86c43290f94c5","_from":".","_npmVersion":"3.10.3","_nodeVersion":"6.3.1","_npmUser":{"name":"qw3rtman","email":"me@nimit.io"},"dist":{"shasum":"7546bc467a120cc96718f2716cd86c43290f94c5","tarball":"https://registry.npmjs.org/n/-/n-2.1.4.tgz"},"maintainers":[{"name":"bat","email":"ben@benatkin.com"},{"name":"qw3rtman","email":"nimit@nimitkalra.com"},{"name":"tedgaydos","email":"tedgaydos@gmail.com"},{"name":"tjholowaychuk","email":"tj@vision-media.ca"},{"name":"tjwebb","email":"me@traviswebb.com"},{"name":"troy0820","email":"troy.connor@yahoo.com"}],"_npmOperationalInternal":{"host":"packages-16-east.internal.npmjs.com","tmp":"tmp/n-2.1.4.tgz_1470600124670_0.21058935346081853"},"directories":{}},"2.1.5":{"name":"n","description":"Interactively Manage All Your Node Versions","version":"2.1.5","author":{"name":"TJ Holowaychuk","email":"tj@vision-media.ca"},"homepage":"https://github.com/tj/n","bugs":{"url":"https://github.com/tj/n/issues"},"contributors":[{"name":"Travis Webb","email":"me@traviswebb.com","url":"tjw.io"},{"name":"Nimit Kalra","email":"me@nimit.io","url":"http://nimit.io"},{"name":"Troy Connor","email":"troy0820@gmail.com","url":"https://github.com/troy0820"}],"keywords":["nvm","node","version","manager","switcher","node","binary","env"],"bin":{"n":"./bin/n"},"repository":{"type":"git","url":"git://github.com/tj/n.git"},"preferGlobal":true,"os":["!win32"],"engines":{"node":"*"},"license":"MIT","gitHead":"cf8b323b4814c280a009344cfec12d6693b09d70","_id":"n@2.1.5","scripts":{},"_shasum":"146a44fbcff3d3f12be7d7bcdd516d796be2e180","_from":".","_npmVersion":"2.15.5","_nodeVersion":"4.4.5","_npmUser":{"name":"troy0820","email":"troy.connor@yahoo.com"},"dist":{"shasum":"146a44fbcff3d3f12be7d7bcdd516d796be2e180","tarball":"https://registry.npmjs.org/n/-/n-2.1.5.tgz"},"maintainers":[{"name":"bat","email":"ben@benatkin.com"},{"name":"qw3rtman","email":"nimit@nimitkalra.com"},{"name":"tedgaydos","email":"tedgaydos@gmail.com"},{"name":"tjholowaychuk","email":"tj@vision-media.ca"},{"name":"tjwebb","email":"me@traviswebb.com"},{"name":"troy0820","email":"troy.connor@yahoo.com"}],"_npmOperationalInternal":{"host":"packages-12-west.internal.npmjs.com","tmp":"tmp/n-2.1.5.tgz_1488994594679_0.9208811118733138"},"directories":{}},"2.1.6":{"name":"n","description":"Interactively Manage All Your Node Versions","version":"2.1.6","author":{"name":"TJ Holowaychuk","email":"tj@vision-media.ca"},"homepage":"https://github.com/tj/n","bugs":{"url":"https://github.com/tj/n/issues"},"contributors":[{"name":"Travis Webb","email":"me@traviswebb.com","url":"tjw.io"},{"name":"Nimit Kalra","email":"me@nimit.io","url":"http://nimit.io"},{"name":"Troy Connor","email":"troy0820@gmail.com","url":"https://github.com/troy0820"}],"keywords":["nvm","node","version","manager","switcher","node","binary","env"],"bin":{"n":"./bin/n"},"repository":{"type":"git","url":"git://github.com/tj/n.git"},"preferGlobal":true,"os":["!win32"],"engines":{"node":"*"},"license":"MIT","gitHead":"661e5ef77e090280c16030eaefe56cf5235f8ab6","_id":"n@2.1.6","scripts":{},"_shasum":"8095d825dde2f66bc8c7b72161394d518a5567c5","_from":".","_npmVersion":"4.4.1","_nodeVersion":"7.7.3","_npmUser":{"name":"troy0820","email":"troy0820@gmail.com"},"dist":{"shasum":"8095d825dde2f66bc8c7b72161394d518a5567c5","tarball":"https://registry.npmjs.org/n/-/n-2.1.6.tgz"},"maintainers":[{"name":"bat","email":"ben@benatkin.com"},{"name":"qw3rtman","email":"nimit@nimitkalra.com"},{"name":"tedgaydos","email":"tedgaydos@gmail.com"},{"name":"tjholowaychuk","email":"tj@vision-media.ca"},{"name":"tjwebb","email":"me@traviswebb.com"},{"name":"troy0820","email":"troy.connor@yahoo.com"}],"_npmOperationalInternal":{"host":"packages-12-west.internal.npmjs.com","tmp":"tmp/n-2.1.6.tgz_1490490358107_0.7631236382294446"},"directories":{}},"2.1.7":{"name":"n","description":"Interactively Manage All Your Node Versions","version":"2.1.7","author":{"name":"TJ Holowaychuk","email":"tj@vision-media.ca"},"homepage":"https://github.com/tj/n","bugs":{"url":"https://github.com/tj/n/issues"},"contributors":[{"name":"Travis Webb","email":"me@traviswebb.com","url":"tjw.io"},{"name":"Nimit Kalra","email":"me@nimit.io","url":"http://nimit.io"},{"name":"Troy Connor","email":"troy0820@gmail.com","url":"https://github.com/troy0820"}],"keywords":["nvm","node","version","manager","switcher","node","binary","env"],"bin":{"n":"./bin/n"},"repository":{"type":"git","url":"git://github.com/tj/n.git"},"preferGlobal":true,"os":["!win32"],"engines":{"node":"*"},"license":"MIT","gitHead":"bcec70577549a9a11d89d10284f8890f0debf6d6","_id":"n@2.1.7","scripts":{},"_shasum":"13fe032a5bed0797983bddf27eb0606517c73c74","_from":".","_npmVersion":"4.4.1","_nodeVersion":"7.7.3","_npmUser":{"name":"troy0820","email":"troy0820@gmail.com"},"dist":{"shasum":"13fe032a5bed0797983bddf27eb0606517c73c74","tarball":"https://registry.npmjs.org/n/-/n-2.1.7.tgz"},"maintainers":[{"name":"bat","email":"ben@benatkin.com"},{"name":"qw3rtman","email":"nimit@nimitkalra.com"},{"name":"tedgaydos","email":"tedgaydos@gmail.com"},{"name":"tjholowaychuk","email":"tj@vision-media.ca"},{"name":"tjwebb","email":"me@traviswebb.com"},{"name":"troy0820","email":"troy.connor@yahoo.com"}],"_npmOperationalInternal":{"host":"packages-12-west.internal.npmjs.com","tmp":"tmp/n-2.1.7.tgz_1490918508873_0.5233936926815659"},"directories":{}},"2.1.8":{"name":"n","description":"Interactively Manage All Your Node Versions","version":"2.1.8","author":{"name":"TJ Holowaychuk","email":"tj@vision-media.ca"},"homepage":"https://github.com/tj/n","bugs":{"url":"https://github.com/tj/n/issues"},"contributors":[{"name":"Travis Webb","email":"me@traviswebb.com","url":"tjw.io"},{"name":"Nimit Kalra","email":"me@nimit.io","url":"http://nimit.io"},{"name":"Troy Connor","email":"troy0820@gmail.com","url":"https://github.com/troy0820"}],"keywords":["nvm","node","version","manager","switcher","node","binary","env"],"bin":{"n":"./bin/n"},"repository":{"type":"git","url":"git://github.com/tj/n.git"},"preferGlobal":true,"os":["!win32"],"engines":{"node":"*"},"license":"MIT","gitHead":"14ab6ff01f3b673e2e29f465a00e0b29643bb8d9","_id":"n@2.1.8","_npmVersion":"5.0.3","_nodeVersion":"8.1.2","_npmUser":{"name":"troy0820","email":"troy0820@gmail.com"},"dist":{"integrity":"sha512-VN3To6jBHSdTHmv+fT00V1nBdj3MWdcOlEKBEaUtXKRqQhuN289B9Jym9P/L3rXfafAsapmh4Fcr/DUR8DGJVg==","shasum":"9b770f6ae0a93c49c64fb614625a63cc5a22d1fd","tarball":"https://registry.npmjs.org/n/-/n-2.1.8.tgz"},"maintainers":[{"name":"bat","email":"ben@benatkin.com"},{"name":"qw3rtman","email":"me@nimit.io"},{"name":"tedgaydos","email":"tedgaydos@gmail.com"},{"name":"tjholowaychuk","email":"tj@vision-media.ca"},{"name":"tjwebb","email":"me@traviswebb.com"},{"name":"troy0820","email":"troy0820@gmail.com"}],"_npmOperationalInternal":{"host":"s3://npm-registry-packages","tmp":"tmp/n-2.1.8.tgz_1498880450388_0.9696143395267427"},"directories":{}}},"maintainers":[{"email":"tedgaydos@gmail.com","name":"tedgaydos"},{"email":"me@nimit.io","name":"qw3rtman"},{"email":"troy0820@gmail.com","name":"troy0820"},{"email":"ben@benatkin.com","name":"bat"},{"email":"me@traviswebb.com","name":"tjwebb"},{"email":"tj@vision-media.ca","name":"tjholowaychuk"}],"time":{"modified":"2018-02-10T14:43:06.105Z","created":"2011-01-05T16:20:52.658Z","0.0.1":"2011-01-05T16:20:52.980Z","0.0.2":"2011-01-05T16:23:38.758Z","0.0.3":"2011-01-05T16:43:56.087Z","0.0.4":"2011-01-05T17:14:46.975Z","0.1.0":"2011-01-05T21:44:43.481Z","0.1.1":"2011-01-14T02:25:33.311Z","0.1.2":"2011-01-21T02:29:24.975Z","0.2.0":"2011-01-21T03:37:45.249Z","0.2.1":"2011-01-21T20:53:07.399Z","0.2.2":"2011-01-21T21:01:40.284Z","0.3.0":"2011-01-22T00:56:08.087Z","0.4.0":"2011-02-14T17:02:52.081Z","0.4.1":"2011-03-13T17:10:21.541Z","0.4.2":"2011-08-03T19:13:15.653Z","0.5.0":"2011-08-08T23:13:30.941Z","0.5.1":"2011-10-11T15:56:13.332Z","0.5.2":"2011-10-14T23:47:54.418Z","0.5.3":"2011-11-04T13:42:41.731Z","0.5.4":"2011-11-05T18:20:50.699Z","0.6.0":"2012-01-26T12:44:59.230Z","0.6.1":"2012-01-26T22:09:00.997Z","0.7.0":"2012-02-22T03:37:29.750Z","0.7.1":"2012-03-14T17:32:00.597Z","0.7.2":"2012-06-14T17:20:45.043Z","0.7.3":"2012-10-08T02:26:17.031Z","0.8.0":"2013-01-18T15:43:25.566Z","0.8.1":"2013-01-18T15:47:46.022Z","0.8.2":"2013-01-18T19:09:53.605Z","0.9.0":"2013-01-19T21:26:40.881Z","0.9.1":"2013-01-21T16:25:30.223Z","0.9.2":"2013-03-12T17:06:58.984Z","0.9.3":"2013-03-12T18:33:19.615Z","1.0.0":"2013-06-26T21:05:17.609Z","1.1.0":"2013-07-10T16:22:22.580Z","1.2.0":"2014-01-30T17:24:26.392Z","1.2.1":"2014-01-31T15:54:05.463Z","1.2.2":"2014-06-28T04:07:40.069Z","1.2.3":"2014-06-28T04:12:29.862Z","1.2.4":"2014-06-28T04:12:55.124Z","1.2.5":"2014-06-28T04:13:26.798Z","1.2.6":"2014-06-28T04:13:59.812Z","1.2.7":"2014-06-28T04:14:24.814Z","1.2.8":"2014-06-28T04:31:18.292Z","1.2.9":"2014-06-29T08:23:22.325Z","1.2.11":"2014-12-28T17:18:00.001Z","1.2.13":"2014-12-28T17:21:14.234Z","1.2.14":"2015-02-25T19:42:58.765Z","1.3.0":"2015-03-21T16:29:32.043Z","1.4.0":"2015-07-19T12:24:59.714Z","2.0.0":"2015-07-19T13:00:16.250Z","1.4.1":"2015-07-19T21:16:32.423Z","2.0.1":"2015-07-19T21:16:55.300Z","1.4.2":"2015-08-15T18:53:32.034Z","2.0.2":"2015-08-15T18:53:50.028Z","2.1.0":"2015-12-29T19:32:22.734Z","2.1.1":"2016-06-16T00:20:12.899Z","2.1.2":"2016-07-05T07:20:37.218Z","2.1.3":"2016-07-12T19:45:45.666Z","2.1.4":"2016-08-07T20:02:06.732Z","2.1.5":"2017-03-08T17:36:36.617Z","2.1.6":"2017-03-26T01:06:00.134Z","2.1.7":"2017-03-31T00:01:50.869Z","2.1.8":"2017-07-01T03:40:51.492Z"},"author":{"name":"TJ Holowaychuk","email":"tj@vision-media.ca"},"users":{"guybrush":true,"aaron":true,"appsunited":true,"bencevans":true,"buritica":true,"sandeepmistry":true,"strathausen":true,"peny":true,"mhaidarh":true,"tetsu3a":true,"t3chnoboy":true,"kerimdzhanov":true,"blakeembrey":true,"flyslow":true,"priyaranjan":true,"tcskrovseth":true,"stewartjarod":true,"monbro":true,"jeffpar":true,"anticom":true,"leizongmin":true,"julien-f":true,"ryaneof":true,"chao2":true,"tjwebb":true,"orion-":true,"joeapearson":true,"csbun":true,"henryfour":true,"trycatch9264":true,"alfjos":true,"pythonic":true,"afc163":true,"dimitriwalters":true,"ellery":true,"thomask33":true,"growlybear":true,"hotell":true,"sean9999a":true,"kulakowka":true,"season19840122":true,"codeshrew":true,"albertpak":true,"markthethomas":true,"nickleefly":true,"vchouhan":true,"52u":true,"bassettsj":true,"francesco-nextology":true,"c1freitas":true,"nex":true,"n370":true,"czll":true,"cristobal-io":true,"dofy":true,"despairblue":true,"maxrimue":true,"philipjc":true,"gaston.elhordoy":true,"incendiary":true,"2dxgujun":true,"jessaustin":true,"matiasmarani":true,"gdaleson":true,"kolomiichenko":true,"rdcl":true,"xgqfrms":true,"monjer":true,"yangmillstheory":true,"dbuggerx":true,"allspeeds":true,"avil13":true,"runningtalus":true,"andr":true,"vwal":true,"luislobo":true,"arbourd":true,"ameer157":true,"flynntsc":true,"makay":true,"rbartoli":true,"sternelee":true,"liushoukai":true,"qw3rtman":true,"timdp":true,"tehdb":true,"evanyeung":true,"biril":true,"slurm":true,"favasconcelos":true,"kevin-smets":true,"justdomepaul":true,"roman-io":true,"figroc":true,"afelicioni":true,"jian263994241":true,"smallhelm":true,"gabrielsanterre":true,"graidenix":true,"farskipper":true,"kruemelo":true,"doomblade":true,"octetstream":true,"adai":true,"schnittstabil":true,"jason0518":true,"eswat2":true,"lizhiqiang":true,"bpatel":true,"vsanjo":true,"adriancmiranda":true,"danielbankhead":true,"sopepos":true,"jedaviata":true,"brainpoint":true,"szymex73":true,"mrodrig":true,"kkk123321":true,"leomperes":true,"max_devjs":true,"edm00se":true,"tdmalone":true,"domjtalbot":true,"llq":true,"ahvonenj":true,"weftech":true,"yinyongcom666":true,"luiscauro":true,"jyounce":true,"post72":true,"shanemileham":true,"trusktr":true,"i3fox":true,"davidjsalazarmoreno":true,"adamlu":true,"sysray":true,"jaxx2104":true,"jasonleewilson":true,"dlv_201":true,"kukulili-labs":true,"strongwray":true,"rocket0191":true,"shuoshubao":true,"qk4":true,"leonzhao":true,"buzz-dee":true,"phpjungle":true,"fengbeijing":true,"modood":true,"4rlekin":true,"xtinctspecies":true,"chbardel":true,"yangwao":true,"keith-":true,"olonam":true,"jmsmrgn":true,"pixel67":true,"sure2darling":true,"gurunate":true,"yunji7":true,"johnrsouth2003":true,"stephenhuh":true,"daniellink":true,"alexbaumgertner":true,"cognivator":true,"enna":true,"netoperatorwibby":true,"lordmidi":true,"xinwangwang":true,"arefm":true,"gauravmehla":true,"detj":true},"repository":{"type":"git","url":"git://github.com/tj/n.git"},"readme":"# `n`  Interactively Manage Your Node.js Versions\n\n[![Join the chat at https://gitter.im/tj/n](https://img.shields.io/gitter/room/tj/n.svg?style=flat-square)](https://gitter.im/tj/n)\n[![npm](https://img.shields.io/npm/dt/n.svg?style=flat-square)](https://www.npmjs.com/package/n)\n[![npm](https://img.shields.io/npm/dm/n.svg?style=flat-square)](https://www.npmjs.com/package/n)\n[![npm](https://img.shields.io/npm/v/n.svg?style=flat-square)](https://www.npmjs.com/package/n)\n[![npm](https://img.shields.io/npm/l/n.svg?style=flat-square)](https://www.npmjs.com/package/n)\n\nNode.js version management: no subshells, no profile setup, no convoluted API, just **simple**.\n\n## **Want to install Node nightly releases? Try [this](https://github.com/tj/n/issues/376#issuecomment-250876666)!**\n\n![](http://nimit.io/images/n/n.gif)\n\n(Unfortunately `n` is not supported on Windows yet. If you're able to make it work, send in a pull request!)\n\n## Installation\n\nSince you probably already have `node`, the easiest way to install `n` is through `npm`:\n\n    $ npm install -g n\n\nAlternatively, you can clone this repo and\n\n    $ make install\n\nto install `n` to `bin/n` of the directory specified in the environment variable `$PREFIX`, which defaults to `/usr/local` (note that you will likely need to use `sudo`). To install `n` in a custom location (such as `$CUSTOM_LOCATION/bin/n`), run `PREFIX=$CUSTOM_LOCATION make install`.\n\nOnce installed, `n` installs `node` versions to subdirectory `n/versions` of the directory specified in environment variable `N_PREFIX`, which defaults to `/usr/local`; the _active_ `node`/`iojs` version is installed directly in `N_PREFIX`.\nTo change the default to, say, `$HOME`, prefix later calls to `n` with `N_PREFIX=$HOME ` or add `export N_PREFIX=$HOME` to your shell initialization file.\n\nAdditionally, consider third-party installer [n-install](https://github.com/mklement0/n-install), which allows installation directly from GitHub; for instance,\n\n    curl -L https://git.io/n-install | bash\n\nsets both `PREFIX` and `N_PREFIX` to `$HOME/n`, installs `n` to `$HOME/n/bin`, modifies the initialization files of supported shells to export `N_PREFIX` and add `$HOME/n/bin` to the `PATH`, and installs the latest stable `node` version.\n\n\nAs a result, both `n` itself and all `node` versions it manages are hosted inside a single, optionally configurable directory, which you can later remove with the included `n-uninstall` script. `n-update` updates `n` itself to the latest version. See the [n-install repo](https://github.com/mklement0/n-install) for more details.\n\n### Installing/Activating Versions\n\nSimply execute `n <version>` to install a version of `node`. If `<version` has already been installed (via `n`), `n` will activate that version.\n\n    $ n 0.8.14\n    $ n 0.8.17\n    $ n 0.9.6\n\nExecute `n` on its own to view your currently installed versions. Use the up and down arrow keys to navigate and press enter or the right arrow key to select. Use ^C (control + C) to exit the selection screen.\nIf you like vim key bindings during the selection of node versions, you can use `j` and `k` to navigate up or down without using arrows. \n\n    $ n\n\n      0.8.14\n     0.8.17\n      0.9.6\n\nUse or install the latest official release:\n\n    $ n latest\n\nUse or install the stable official release:\n\n    $ n stable\n\nUse or install the latest LTS official release:\n\n    $ n lts\n\n### Removing Versions\n\nRemove some versions:\n\n    $ n rm 0.9.4 v0.10.0\n\nAlternatively, you can use `-` in lieu of `rm`:\n\n    $ n - 0.9.4\n\nRemoving all versions except the current version:\n\n```bash\n$ n prune \n```\n\n### Binary Usage\n\nWhen running multiple versions of `node`, we can target\nthem directly by asking `n` for the binary path:\n\n    $ n bin 0.9.4\n    /usr/local/n/versions/0.9.4/bin/node\n\nOr by using a specific version through `n`'s `use` sub-command:\n\n    $ n use 0.9.4 some.js\n\nFlags also work here:\n\n    $ n as 0.9.4 --debug some.js\n\n### Working with `npm`\n\nAfter switching Node.js versions using `n`, `npm` may not work properly. This should fix it (thanks [@mikemoser](https://github.com/mikemoser)!):\n\n```sh\n$ curl -0 -L https://npmjs.com/install.sh | sudo sh\n```\n\n`sudo` may not be required depending on your system configuration.\n\n## Usage\n\nOutput can also be obtained from `n --help`.\n\n    Usage: n [options/env] [COMMAND] [args]\n\n    Environments:\n     n [COMMAND] [args]            Uses default env (node)\n     n io [COMMAND]                Sets env as io\n\n    Commands:\n\n      n                              Output versions installed\n      n latest                       Install or activate the latest node release\n      n -a x86 latest                As above but force 32 bit architecture\n      n stable                       Install or activate the latest stable node release\n      n lts                          Install or activate the latest LTS node release\n      n <version>                    Install node <version>\n      n use <version> [args ...]     Execute node <version> with [args ...]\n      n bin <version>                Output bin path for <version>\n      n rm <version ...>             Remove the given version(s)\n      n prune                        Remove all versions except the current version\n      n --latest                     Output the latest node version available\n      n --stable                     Output the latest stable node version available\n      n --lts                        Output the latest LTS node version available\n      n ls                           Output the versions of node available\n\n    (iojs):\n\n      n io latest                    Install or activate the latest iojs release\n      n io -a x86 latest             As above but force 32 bit architecture\n      n io <version>                 Install iojs <version>\n      n io use <version> [args ...]  Execute iojs <version> with [args ...]\n      n io bin <version>             Output bin path for <version>\n      n io rm <version ...>          Remove the given version(s)\n      n io --latest                  Output the latest iojs version available\n      n io ls                        Output the versions of iojs available\n\n    Options:\n\n      -V, --version   Output current version of n\n      -h, --help      Display help information\n      -q, --quiet     Disable curl output (if available)\n      -d, --download  Download only\n      -a, --arch      Override system architecture\n\n    Aliases:\n\n      which   bin\n      use     as\n      list    ls\n      -       rm\n\n## Custom source\n\nIf you would like to use a project other than the official Node.js or io.js projects, you can use the special `n project [command]` which allows you to control the behavior of `n` using environment variables.\n\nFor example, to grab the latest io.js version but name it \"foo\" instead,\n\n      PROJECT_NAME=\"foo\" PROJECT_URL=\"https://iojs.org/dist/\" n project latest\n\nRequired Variables:\n\n* `PROJECT_NAME`: The name the project will be stored under\n* `PROJECT_URL`: The location to download the project from. Note, this must follow the same format as the io.js/Node.js repos\n\nOptional Variables:\n\n* `HTTP_USER`: The username if the `PROJECT_URL` is protected by basic authentication\n* `HTTP_PASSWORD`: The password if the `PROJECT_URL` is protected by basic authentication\n* `PROJECT_VERSION_CHECK`: Many custom projects keep the same version number as the Node.js release they are based on, and maintain their own separate version in process. This allows you to define a JavaScript variable that will be used to check for the version of the process, for example: `process.versions.node`\n\n## Custom architecture\n\nBy default `n` picks the binaries matching your system architecture, e.g. `n` will download 64 bit binaries for a 64 bit system. You can override this by using the `-a` or `--arch` option.\n\nDownload and use latest 32 bit version of `node`:\n\n    $ n --arch x86 latest\n\nDownload and use latest 32 bit version of `iojs`:\n\n    $ n io --arch x86 latest\n\nDownload and use 64 bit LTS version of `node` for older Mac Intel Core 2 Duo systems (x86 image is no longer available but x64 runs fine):\n\n    $ n --arch x64 lts\n\n## Additional Details\n\n`n` installs versions to `/usr/local/n/versions` by default. Here, it can see what versions are currently installed and activate previously installed versions accordingly when `n <version>` is invoked again.\n\nActivated versions are then installed to the prefix `/usr/local`, which may be altered via the __`N_PREFIX`__ environment variable.\n\nTo alter where `n` operates, simply `export N_PREFIX`.\n\n`n` does not work on Windows at the moment. Pull Requests are appreciated.\n\nIf you are searching for the latest version of `n` below 2.x.x, check out the branch `1.x.x`.\n\n## Core Team\n\n* Nimit Kalra  [@qw3rtman](https://github.com/qw3rtman)\n* Ted Gaydos  [@tedgaydos](https://github.com/tedgaydos)\n* Travis Webb  [@tjwebb](https://github.com/tjwebb)\n\nPlease Read [Contributing Docs](https://github.com/tj/n/blob/master/.github/CONTRIBUTING.md)\n\n## License\n\n(The MIT License)\n\nCopyright (c) 2014 TJ Holowaychuk &lt;tj@vision-media.ca&gt;\n\nPermission is hereby granted, free of charge, to any person obtaining\na copy of this software and associated documentation files (the\n'Software'), to deal in the Software without restriction, including\nwithout limitation the rights to use, copy, modify, merge, publish,\ndistribute, sublicense, and/or sell copies of the Software, and to\npermit persons to whom the Software is furnished to do so, subject to\nthe following conditions:\n\nThe above copyright notice and this permission notice shall be\nincluded in all copies or substantial portions of the Software.\n\nTHE SOFTWARE IS PROVIDED 'AS IS', WITHOUT WARRANTY OF ANY KIND,\nEXPRESS OR IMPLIED, INCLUDING BUT NOT LIMITED TO THE WARRANTIES OF\nMERCHANTABILITY, FITNESS FOR A PARTICULAR PURPOSE AND NONINFRINGEMENT.\nIN NO EVENT SHALL THE AUTHORS OR COPYRIGHT HOLDERS BE LIABLE FOR ANY\nCLAIM, DAMAGES OR OTHER LIABILITY, WHETHER IN AN ACTION OF CONTRACT,\nTORT OR OTHERWISE, ARISING FROM, OUT OF OR IN CONNECTION WITH THE\nSOFTWARE OR THE USE OR OTHER DEALINGS IN THE SOFTWARE.\n","readmeFilename":"README.md","homepage":"https://github.com/tj/n","keywords":["nvm","node","version","manager","switcher","node","binary","env"],"bugs":{"url":"https://github.com/tj/n/issues"},"license":"MIT","contributors":[{"name":"Travis Webb","email":"me@traviswebb.com","url":"tjw.io"},{"name":"Nimit Kalra","email":"me@nimit.io","url":"http://nimit.io"},{"name":"Troy Connor","email":"troy0820@gmail.com","url":"https://github.com/troy0820"}],"_attachments":{},"_etag":"\"5a7f04fa-11737\""}